vonage_number_insight_v2/__init__.py
vonage_number_insight_v2/errors.py
vonage_number_insight_v2/number_insight_v2.py
vonage_number_insight_v2-0.1.0.dist-info/METADATA
vonage_number_insight_v2-0.1.0.dist-info/WHEEL
vonage_number_insight_v2-0.1.0.dist-info/top_level.txt
vonage_number_insight_v2-0.1.0.dist-info/RECORD
