Metadata-Version: 2.1
Name: vonage-number-insight-v2
Version: 0.1.0
Summary: Vonage Number Insight v2 package
Author-email: Vonage <devrel@vonage.com>
Project-URL: homepage, https://github.com/Vonage/vonage-python-sdk
Classifier: Programming Language :: Python
Classifier: Programming Language :: Python :: 3
Classifier: Programming Language :: Python :: 3.8
Classifier: Programming Language :: Python :: 3.9
Classifier: Programming Language :: Python :: 3.10
Classifier: Programming Language :: Python :: 3.11
Classifier: Programming Language :: Python :: 3.12
Classifier: License :: OSI Approved :: Apache Software License
Requires-Python: >=3.8
Requires-Dist: vonage-http-client >=1.0.0
Requires-Dist: vonage-utils >=1.0.0
Requires-Dist: pydantic >=2.6.1
